textcatvis/__init__.py
textcatvis/check_query.py
textcatvis/cluster.py
textcatvis/data_utils.py
textcatvis/distinctive_words.py
textcatvis/vis_utils.py
textcatvis/visualize_relevantwords.py
textcatvis-1.0.4.dist-info/DESCRIPTION.rst
textcatvis-1.0.4.dist-info/METADATA
textcatvis-1.0.4.dist-info/RECORD
textcatvis-1.0.4.dist-info/WHEEL
textcatvis-1.0.4.dist-info/metadata.json
textcatvis-1.0.4.dist-info/top_level.txt
