Metadata-Version: 2.0
Name: textcatvis
Version: 1.0.4
Summary: Text Dataset Categories/Clusters Visualization with Word Clouds
Home-page: https://github.com/cod3licious/textcatvis
Author: cod3licious
Author-email: cod3licious@gmail.com
License: MIT
Keywords: natural language processing text processing visualization wordcloud lrp
Platform: UNKNOWN
Classifier: Development Status :: 3 - Alpha
Classifier: Intended Audience :: Science/Research
Classifier: Topic :: Scientific/Engineering :: Artificial Intelligence
Classifier: License :: OSI Approved :: MIT License
Classifier: Programming Language :: Python :: 2
Classifier: Programming Language :: Python :: 2.7
Classifier: Programming Language :: Python :: 3
Classifier: Programming Language :: Python :: 3.4
Classifier: Programming Language :: Python :: 3.5
Classifier: Programming Language :: Python :: 3.6
Requires-Dist: future
Requires-Dist: numpy
Requires-Dist: scipy
Requires-Dist: scikit-learn
Requires-Dist: matplotlib
Requires-Dist: wordcloud
Requires-Dist: nlputils
